llm_youtube.py
llm_youtube-0.1.dist-info/licenses/LICENSE
llm_youtube-0.1.dist-info/METADATA
llm_youtube-0.1.dist-info/WHEEL
llm_youtube-0.1.dist-info/entry_points.txt
llm_youtube-0.1.dist-info/top_level.txt
llm_youtube-0.1.dist-info/RECORD
