Metadata-Version: 2.4
Name: llm-youtube
Version: 0.1
Summary: LLM plugin for pulling content from Youtube videos
Author: irfansofyana
License: Apache-2.0
Project-URL: Homepage, https://github.com/irfansofyana/llm-youtube
Project-URL: Changelog, https://github.com/irfansofyana/llm-youtube/releases
Project-URL: Issues, https://github.com/irfansofyana/llm-youtube/issues
Project-URL: CI, https://github.com/irfansofyana/llm-youtube/actions
Requires-Python: >=3.9
License-File: LICENSE
Requires-Dist: llm>=0.24
Requires-Dist: youtube_transcript_api>=1.0.3
Provides-Extra: test
Requires-Dist: pytest; extra == "test"
Requires-Dist: youtube_transcript_api; extra == "test"
Dynamic: license-file
